pyfrete/__init__.py
pyfrete/correios.py
pyfrete-0.1.2.dist-info/LICENSE
pyfrete-0.1.2.dist-info/METADATA
pyfrete-0.1.2.dist-info/WHEEL
pyfrete-0.1.2.dist-info/top_level.txt
pyfrete-0.1.2.dist-info/RECORD
