Metadata-Version: 2.1
Name: pyfrete
Version: 0.1.2
Summary: API for Brazillian Shipping Methods in Python
Home-page: https://github.com/felipevisu/pyfrete
Author: Felipe Faria
Author-email: felipevisu@gmail.com
License: BSD 2-clause
Platform: UNKNOWN
Classifier: Development Status :: 4 - Beta
Classifier: Intended Audience :: Developers
Classifier: License :: OSI Approved :: MIT License
Classifier: Operating System :: OS Independent
Classifier: Programming Language :: Python
Classifier: Topic :: Software Development :: Libraries :: Python Modules
Requires-Python: >=3.6
Requires-Dist: zeep (>=3)
Requires-Dist: zipp (>=3)
